IservETLLib/DatabaseManager.py
IservETLLib/Helpers.py
IservETLLib/LogManager.py
IservETLLib/__init__.py
IservETLLib/index.py
iservetllib-0.0.18.dist-info/licenses/LICENSE
iservetllib-0.0.18.dist-info/METADATA
iservetllib-0.0.18.dist-info/WHEEL
iservetllib-0.0.18.dist-info/top_level.txt
iservetllib-0.0.18.dist-info/RECORD
