Metadata-Version: 2.4
Name: IservETLLib
Version: 0.0.18
Summary: Общий код для ETL jupiter notebooks
Author-email: k-avtonomov <k-avtonomov@it-serv.ru>, a-kostyuhin <a-kostyuhin@it-serv.ru>
License-Expression: MIT
Classifier: Programming Language :: Python :: 3
Classifier: Operating System :: OS Independent
Requires-Python: >=3.9
License-File: LICENSE
Requires-Dist: fluent-logger>=0.11.1
Requires-Dist: pandas>=2.0.0
Requires-Dist: SQLAlchemy>=2.0.43
Requires-Dist: numpy>=1.26.4
Requires-Dist: openpyxl>=3.1.2
Dynamic: license-file
